taplite/__init__.py
taplite/libtaplite.so
taplite/libtaplite_arm.dylib
taplite/libtaplite_x64.dylib
taplite/taplite.dll
taplite/taplite.py
taplite-0.1.2.dist-info/METADATA
taplite-0.1.2.dist-info/WHEEL
taplite-0.1.2.dist-info/top_level.txt
taplite-0.1.2.dist-info/RECORD
