Metadata-Version: 2.4
Name: taplite
Version: 0.1.2
Summary: A lightweight traffic assignment and simulation engine for networks encoded in GMNS
Home-page: https://github.com/asu-trans-ai-lab/TAPLite
Author: Dr. Xuesong Zhou, Dr. Peiheng Li
Author-email: xzhou74@asu.edu, jdlph@hotmail.com
License: Apache License 2.0
Classifier: Programming Language :: Python :: 3
Classifier: License :: OSI Approved :: Apache Software License
Classifier: Operating System :: OS Independent
Dynamic: author
Dynamic: author-email
Dynamic: classifier
Dynamic: description
Dynamic: description-content-type
Dynamic: home-page
Dynamic: license
Dynamic: summary
